README.rst
setup.py
bark/__init__.py
bark/bark.py
bark_ssg.egg-info/PKG-INFO
bark_ssg.egg-info/SOURCES.txt
bark_ssg.egg-info/dependency_links.txt
bark_ssg.egg-info/entry_points.txt
bark_ssg.egg-info/requires.txt
bark_ssg.egg-info/top_level.txt