Metadata-Version: 1.1
Name: bark-ssg
Version: 1.3.2
Summary: Single file static site generator.
Home-page: https://github.com/battleroid/bark
Author: Casey Weed
Author-email: me@caseyweed.net
License: MIT License
Download-URL: https://github.com/battleroid/bark/tarball/master
Keywords: bark static site generator jinja blog python markdown
Platform: any
Classifier: Programming Language :: Python
Classifier: Topic :: Internet
Classifier: Topic :: Internet :: WWW/HTTP :: Site Management
Classifier: Topic :: Text Processing
Classifier: Topic :: Text Processing :: Markup
Classifier: Topic :: Text Processing :: Markup :: HTML
